{"results": [{"conv_id": "conv-26", "q_idx": 0, "category": 2, "category_name": "temporal", "question": "When did Caroline go to the LGBTQ support group?", "ground_truth": "7 May 2023", "prediction": "Caroline went to the LGBTQ support group yesterday.", "score": 0}, {"conv_id": "conv-26", "q_idx": 1, "category": 2, "category_name": "temporal", "question": "When did Melanie paint a sunrise?", "ground_truth": 2022, "prediction": "Melanie painted lake sunrise last year.", "score": 0}, {"conv_id": "conv-26", "q_idx": 2, "category": 3, "category_name": "open_domain", "question": "What fields would Caroline be likely to pursue in her educaton?", "ground_truth": "Psychology, counseling certification", "prediction": "Caroline is looking into counseling and mental health jobs and plans to continue education in these fields.", "score": 1}, {"conv_id": "conv-26", "q_idx": 3, "category": 1, "category_name": "multi_hop", "question": "What did Caroline research?", "ground_truth": "Adoption agencies", "prediction": "Caroline is researching adoption agencies.", "score": 1}, {"conv_id": "conv-26", "q_idx": 4, "category": 1, "category_name": "multi_hop", "question": "What is Caroline's identity?", "ground_truth": "Transgender woman", "prediction": "Caroline is a transgender woman.", "score": 1}, {"conv_id": "conv-26", "q_idx": 5, "category": 2, "category_name": "temporal", "question": "When did Melanie run a charity race?", "ground_truth": "The sunday before 25 May 2023", "prediction": "Melanie ran the charity race on last Saturday.", "score": 0}, {"conv_id": "conv-26", "q_idx": 6, "category": 2, "category_name": "temporal", "question": "When is Melanie planning on going camping?", "ground_truth": "June 2023", "prediction": "Melanie is thinking about going camping next month.", "score": 0}, {"conv_id": "conv-26", "q_idx": 7, "category": 1, "category_name": "multi_hop", "question": "What is Caroline's relationship status?", "ground_truth": "Single", "prediction": "The memories do not contain this information.", "score": 0}, {"conv_id": "conv-26", "q_idx": 8, "category": 2, "category_name": "temporal", "question": "When did Caroline give a speech at a school?", "ground_truth": "The week before 9 June 2023", "prediction": "The memories do not contain this information.", "score": 0}, {"conv_id": "conv-26", "q_idx": 9, "category": 2, "category_name": "temporal", "question": "When did Caroline meet up with her friends, family, and mentors?", "ground_truth": "The week before 9 June 2023", "prediction": "Caroline met up with her friends and family for a picnic last week.", "score": 0}, {"conv_id": "conv-26", "q_idx": 10, "category": 2, "category_name": "temporal", "question": "How long has Caroline had her current group of friends for?", "ground_truth": "4 years", "prediction": "Caroline has known her friends for 4 years.", "score": 1}, {"conv_id": "conv-26", "q_idx": 11, "category": 1, "category_name": "multi_hop", "question": "Where did Caroline move from 4 years ago?", "ground_truth": "Sweden", "prediction": "Caroline moved from Sweden.", "score": 1}, {"conv_id": "conv-26", "q_idx": 12, "category": 2, "category_name": "temporal", "question": "How long ago was Caroline's 18th birthday?", "ground_truth": "10 years ago", "prediction": "The memories do not contain this information.", "score": 0}, {"conv_id": "conv-26", "q_idx": 13, "category": 1, "category_name": "multi_hop", "question": "What career path has Caroline decided to persue?", "ground_truth": "counseling or mental health for Transgender people", "prediction": "Caroline has decided to pursue a career in counseling and mental health.", "score": 0}, {"conv_id": "conv-26", "q_idx": 14, "category": 3, "category_name": "open_domain", "question": "Would Caroline still want to pursue counseling as a career if she hadn't received support growing up?", "ground_truth": "Likely no", "prediction": "The memories do not contain this information.", "score": 0}, {"conv_id": "conv-26", "q_idx": 15, "category": 1, "category_name": "multi_hop", "question": "What activities does Melanie partake in?", "ground_truth": "pottery, camping, painting, swimming", "prediction": "Melanie partakes in pottery class, where she made a plate yesterday, and painting activities with her kids, during which they found lovely flowers. She also participates in a charity race.", "score": 0}, {"conv_id": "conv-26", "q_idx": 16, "category": 2, "category_name": "temporal", "question": "When did Melanie sign up for a pottery class?", "ground_truth": "2 July 2023", "prediction": "Melanie signed up for pottery class yesterday.", "score": 0}, {"conv_id": "conv-26", "q_idx": 17, "category": 2, "category_name": "temporal", "question": "When is Caroline going to the transgender conference?", "ground_truth": "July 2023", "prediction": "Caroline is going to the transgender conference this month.", "score": 0}, {"conv_id": "conv-26", "q_idx": 18, "category": 1, "category_name": "multi_hop", "question": "Where has Melanie camped?", "ground_truth": "beach, mountains, forest", "prediction": "Melanie has camped in the mountains and at the beach.", "score": 0}, {"conv_id": "conv-26", "q_idx": 19, "category": 1, "category_name": "multi_hop", "question": "What do Melanie's kids like?", "ground_truth": "dinosaurs, nature", "prediction": "Melanie's 2 younger kids love nature. Her kids had a blast at the beach recently, loved the camping trip, and had fun exploring and playing at the park.", "score": 0}, {"conv_id": "conv-26", "q_idx": 20, "category": 2, "category_name": "temporal", "question": "When did Melanie go to the museum?", "ground_truth": "5 July 2023", "prediction": "Melanie took kids to the museum yesterday.", "score": 0}, {"conv_id": "conv-26", "q_idx": 21, "category": 2, "category_name": "temporal", "question": "When did Caroline have a picnic?", "ground_truth": "The week before 6 July 2023", "prediction": "Caroline and friends and family had a picnic last week.", "score": 0}, {"conv_id": "conv-26", "q_idx": 22, "category": 3, "category_name": "open_domain", "question": "Would Caroline likely have Dr. Seuss books on her bookshelf?", "ground_truth": "Yes, since she collects classic children's books", "prediction": "The memories do not contain this information.", "score": 0}, {"conv_id": "conv-26", "q_idx": 23, "category": 1, "category_name": "multi_hop", "question": "What books has Melanie read?", "ground_truth": "\"Nothing is Impossible\", \"Charlotte's Web\"", "prediction": "Melanie has read the book recommended by Caroline and loved reading the book Charlotte's Web.", "score": 0}, {"conv_id": "conv-26", "q_idx": 24, "category": 1, "category_name": "multi_hop", "question": "What does Melanie do to destress?", "ground_truth": "Running, pottery", "prediction": "Melanie plays clarinet as a way to relax and carves out me-time each day playing violin.", "score": 0}, {"conv_id": "conv-26", "q_idx": 25, "category": 2, "category_name": "temporal", "question": "When did Caroline go to the LGBTQ conference?", "ground_truth": "10 July 2023", "prediction": "Caroline went to the LGBTQ conference two days ago.", "score": 0}, {"conv_id": "conv-26", "q_idx": 26, "category": 2, "category_name": "temporal", "question": "When did Melanie read the book \"nothing is impossible\"?", "ground_truth": 2022, "prediction": "The memories do not contain this information.", "score": 0}, {"conv_id": "conv-26", "q_idx": 27, "category": 3, "category_name": "open_domain", "question": "Would Caroline pursue writing as a career option?", "ground_truth": "LIkely no; though she likes reading, she wants to be a counselor", "prediction": "The memories do not contain this information.", "score": 0}, {"conv_id": "conv-26", "q_idx": 28, "category": 2, "category_name": "temporal", "question": "When did Caroline go to the adoption meeting?", "ground_truth": "The friday before 15 July 2023", "prediction": "Caroline went to the council meeting for adoption on last Friday.", "score": 0}, {"conv_id": "conv-26", "q_idx": 29, "category": 2, "category_name": "temporal", "question": "When did Melanie go to the pottery workshop?", "ground_truth": "The Friday before 15 July 2023", "prediction": "Melanie took kids to pottery workshop on last Friday.", "score": 0}, {"conv_id": "conv-26", "q_idx": 30, "category": 3, "category_name": "open_domain", "question": "Would Melanie be considered a member of the LGBTQ community?", "ground_truth": "Likely no, she does not refer to herself as part of it", "prediction": "The memories do not contain this information.", "score": 0}]}